{
  "date": "2024-02-18T08:19:33+07:00",
  "heading": "",
  "about_image": "images/projects/kenmore-treeside/office portrait.jpg",
  "description": "Hello there 👋! I'm Neha, the founding designer at NU Curations, where we believe in more than just designing spaces – we're here to build personal connections. Our approach is all about crafting designs that truly reflect your lifestyle and aspirations. With us, you'll experience a seamless journey through the design process, filled with excitement at every turn.\n\nAt NU Curations, functionality is at the forefront of our priorities. We ensure that your space not only looks exceptional but lives exceptionally well too. Whether you're looking to transform one room or your entire home, we're dedicated to discovering creative, aesthetic solutions that perfectly express your style while staying within your budget.\n\nLet's work together to turn your vision into a harmonious, functional, and utterly gorgeous reality.",
  "expertise_title": "Expertise",
  "expertise_sectors": [
    "Midcentury Modern",
    "Vintage",
    "Coastal",
    "Contemporary",
    "Rustic",
    "Industrial",
    "Shabby Chic"
  ]
}
